fly_log/__init__.py
fly_log/fly_log.py
fly_log/fly_log_sample_dev_run.py
fly_log-0.3.1.dist-info/LICENSE
fly_log-0.3.1.dist-info/METADATA
fly_log-0.3.1.dist-info/WHEEL
fly_log-0.3.1.dist-info/top_level.txt
fly_log-0.3.1.dist-info/RECORD
