Metadata-Version: 2.1
Name: fly-log
Version: 0.3.1
Summary: a simple log for small project
Home-page: https://github.com/zero-space-man-community/fly_log
Author: flythinker
Author-email: flythinker@qq.com
License: MIT License
Keywords: fly log debug
Platform: any
Classifier: Intended Audience :: Developers
Classifier: License :: OSI Approved :: MIT License
Classifier: Operating System :: OS Independent
Classifier: Programming Language :: Python
Classifier: Programming Language :: Python :: 3
License-File: LICENSE
